drf_api_logger_with_user/__init__.py
drf_api_logger_with_user/admin.py
drf_api_logger_with_user/apps.py
drf_api_logger_with_user/collectstatic.py
drf_api_logger_with_user/events.py
drf_api_logger_with_user/insert_log_into_database.py
drf_api_logger_with_user/models.py
drf_api_logger_with_user/start_logger_when_server_starts.py
drf_api_logger_with_user/tests.py
drf_api_logger_with_user/utils.py
drf_api_logger_with_user/middleware/__init__.py
drf_api_logger_with_user/middleware/api_logger_middleware.py
drf_api_logger_with_user/migrations/0001_initial.py
drf_api_logger_with_user/migrations/__init__.py
drf_api_logger_with_user/templates/change_form.html
drf_api_logger_with_user/templates/charts_change_list.html
drf_api_logger_with_user-1.3.0.dist-info/LICENSE
drf_api_logger_with_user-1.3.0.dist-info/METADATA
drf_api_logger_with_user-1.3.0.dist-info/WHEEL
drf_api_logger_with_user-1.3.0.dist-info/top_level.txt
drf_api_logger_with_user-1.3.0.dist-info/RECORD
