Metadata-Version: 2.1
Name: drf-api-logger-with-user
Version: 1.3.0
Summary: An API Logger for your Django Rest Framework project.
Home-page: https://github.com/HAM1DR37A/DRF-API-Logger/
Author: Hamid Soltani
Author-email: pandora10mk@gmail.com
License: Apache 2.0
Platform: UNKNOWN
Classifier: Programming Language :: Python :: 3.6
Classifier: Programming Language :: Python :: 3.7
Classifier: Programming Language :: Python :: 3.8
Classifier: Programming Language :: Python :: 3.9
Classifier: Operating System :: OS Independent
Requires-Python: >=3.6
License-File: LICENSE
Requires-Dist: djangorestframework (>=3.7.4)
Requires-Dist: bleach (>=3.1.5)
